WheelTest/__init__.py
WheelTest/functions.py
WheelTest/main.py
WheelTest/variables.py
WheelTest-0.1.dist-info/METADATA
WheelTest-0.1.dist-info/WHEEL
WheelTest-0.1.dist-info/top_level.txt
WheelTest-0.1.dist-info/RECORD
