Metadata-Version: 2.1
Name: WheelTest
Version: 0.1
Summary: just a test
Home-page: UNKNOWN
Author: Erik Fumi
Author-email: erikfumi@gmail.com
License: UNKNOWN
Platform: UNKNOWN
Requires-Dist: numpy
